MANIFEST.in
requirements.txt
setup.py
django_sloth.egg-info/PKG-INFO
django_sloth.egg-info/SOURCES.txt
django_sloth.egg-info/dependency_links.txt
django_sloth.egg-info/requires.txt
django_sloth.egg-info/top_level.txt
sloth/.DS_Store
sloth/Dockerfile
sloth/__init__.py
sloth/__main__.py
sloth/.idea/modules.xml
sloth/.idea/sloth.iml
sloth/.idea/workspace.xml
sloth/.idea/inspectionProfiles/profiles_settings.xml
sloth/__pycache__/__init__.cpython-310.pyc
sloth/__pycache__/__init__.cpython-38.pyc
sloth/__pycache__/__main__.cpython-38.pyc
sloth/actions/__init__.py
sloth/actions/fields.py
sloth/actions/inputs.py
sloth/actions/__pycache__/__init__.cpython-310.pyc
sloth/actions/__pycache__/__init__.cpython-38.pyc
sloth/actions/__pycache__/fields.cpython-310.pyc
sloth/actions/__pycache__/fields.cpython-38.pyc
sloth/actions/__pycache__/inputs.cpython-310.pyc
sloth/actions/__pycache__/inputs.cpython-38.pyc
sloth/api/__init__.py
sloth/api/actions.py
sloth/api/dashboard.py
sloth/api/models.py
sloth/api/urls.py
sloth/api/views.py
sloth/api/__pycache__/__init__.cpython-310.pyc
sloth/api/__pycache__/__init__.cpython-38.pyc
sloth/api/__pycache__/actions.cpython-310.pyc
sloth/api/__pycache__/actions.cpython-38.pyc
sloth/api/__pycache__/dashboard.cpython-38.pyc
sloth/api/__pycache__/models.cpython-310.pyc
sloth/api/__pycache__/models.cpython-38.pyc
sloth/api/__pycache__/urls.cpython-310.pyc
sloth/api/__pycache__/urls.cpython-38.pyc
sloth/api/__pycache__/views.cpython-310.pyc
sloth/api/__pycache__/views.cpython-38.pyc
sloth/api/backends/__init__.py
sloth/api/backends/__pycache__/__init__.cpython-38.pyc
sloth/api/exceptions/__init__.py
sloth/api/exceptions/__pycache__/__init__.cpython-38.pyc
sloth/api/management/__init__.py
sloth/api/management/__pycache__/__init__.cpython-310.pyc
sloth/api/management/__pycache__/__init__.cpython-38.pyc
sloth/api/management/commands/__init__.py
sloth/api/management/commands/cloud.py
sloth/api/management/commands/query.py
sloth/api/management/commands/reset_passwords.py
sloth/api/management/commands/selenium.py
sloth/api/management/commands/send_web_push_notification.py
sloth/api/management/commands/startserver.py
